[
    {
        "key": "datr",
        "value": "cw5haDdOa9BX_0szK8HOYJVz",
        "domain": "facebook.com",
        "path": "/",
        "hostOnly": false,
        "creation": "2025-06-29T15:15:06.200Z",
        "lastAccessed": "2025-06-29T15:15:06.200Z"
    },
    {
        "key": "sb",
        "value": "cw5haCOkMpDwXlbiOr_I-VDs",
        "domain": "facebook.com",
        "path": "/",
        "hostOnly": false,
        "creation": "2025-06-29T15:15:06.200Z",
        "lastAccessed": "2025-06-29T15:15:06.200Z"
    },
    {
        "key": "c_user",
        "value": "61577620543563",
        "domain": "facebook.com",
        "path": "/",
        "hostOnly": false,
        "creation": "2025-06-29T15:15:06.200Z",
        "lastAccessed": "2025-06-29T15:15:06.200Z"
    },
    {
        "key": "locale",
        "value": "en_GB",
        "domain": "facebook.com",
        "path": "/",
        "hostOnly": false,
        "creation": "2025-06-29T15:15:06.200Z",
        "lastAccessed": "2025-06-29T15:15:06.200Z"
    },
    {
        "key": "dpr",
        "value": "4.269898891448975",
        "domain": "facebook.com",
        "path": "/",
        "hostOnly": false,
        "creation": "2025-06-29T15:15:06.200Z",
        "lastAccessed": "2025-06-29T15:15:06.200Z"
    },
    {
        "key": "wd",
        "value": "774x1508",
        "domain": "facebook.com",
        "path": "/",
        "hostOnly": false,
        "creation": "2025-06-29T15:15:06.200Z",
        "lastAccessed": "2025-06-29T15:15:06.200Z"
    },
    {
        "key": "presence",
        "value": "C%7B%22t3%22%3A%5B%5D%2C%22utc3%22%3A1751210103539%2C%22v%22%3A1%7D",
        "domain": "facebook.com",
        "path": "/",
        "hostOnly": false,
        "creation": "2025-06-29T15:15:06.200Z",
        "lastAccessed": "2025-06-29T15:15:06.200Z"
    },
    {
        "key": "fr",
        "value": "1tmiFiuZAs7tzpZx5.AWcCeCEwKnXQcqQHglw1Yh3SRo2QVa9MK1c860nxXOFufR_7QkI.BoYVh4..AAA.0.0.BoYVh4.AWdhF5fzzOPgU-IzRPzSxciEa9w",
        "domain": "facebook.com",
        "path": "/",
        "hostOnly": false,
        "creation": "2025-06-29T15:15:06.200Z",
        "lastAccessed": "2025-06-29T15:15:06.200Z"
    },
    {
        "key": "xs",
        "value": "15%3AXIHftzoXscW-ng%3A2%3A1751191218%3A-1%3A-1%3A%3AAcXYleY96RzZQofhRePZJ4UgEd7HHPwfzQhnQO1N5A",
        "domain": "facebook.com",
        "path": "/",
        "hostOnly": false,
        "creation": "2025-06-29T15:15:06.200Z",
        "lastAccessed": "2025-06-29T15:15:06.200Z"
    }
        ]
